dbagent/__init__.py
dbagent/cli.py
dbagent/version.py
dbagent-0.0.1.dist-info/licenses/LICENSE
dbagent-0.0.1.dist-info/METADATA
dbagent-0.0.1.dist-info/WHEEL
dbagent-0.0.1.dist-info/entry_points.txt
dbagent-0.0.1.dist-info/top_level.txt
dbagent-0.0.1.dist-info/RECORD
